wiki_matcher/compare.py
wiki_matcher/ignore.py
wiki_matcher/match.py
wiki_matcher/wiki.py
wiki_matcher/wiki_parser.py
wiki_matcher-0.0.2.dist-info/LICENSE
wiki_matcher-0.0.2.dist-info/METADATA
wiki_matcher-0.0.2.dist-info/WHEEL
wiki_matcher-0.0.2.dist-info/top_level.txt
wiki_matcher-0.0.2.dist-info/RECORD
